jupyterbook_latex/__init__.py
jupyterbook_latex/events.py
jupyterbook_latex/nodes.py
jupyterbook_latex/py.typed
jupyterbook_latex/transforms.py
jupyterbook_latex/theme/__init__.py
jupyterbook_latex/theme/jupyterBook.cls
jupyterbook_latex-0.3.1.dist-info/LICENSE
jupyterbook_latex-0.3.1.dist-info/METADATA
jupyterbook_latex-0.3.1.dist-info/WHEEL
jupyterbook_latex-0.3.1.dist-info/top_level.txt
jupyterbook_latex-0.3.1.dist-info/RECORD
