Metadata-Version: 2.1
Name: jupyterbook-latex
Version: 0.3.1
Summary: Latex specific features for jupyter book
Home-page: https://executablebooks.org/
Author: Executable Book Project
Author-email: jupyter@googlegroups.com
License: BSD-3-Clause
Platform: UNKNOWN
Classifier: License :: OSI Approved :: BSD License
Classifier: Programming Language :: Python :: 3
Classifier: Programming Language :: Python :: 3 :: Only
Classifier: Programming Language :: Python :: 3.6
Classifier: Programming Language :: Python :: 3.7
Classifier: Programming Language :: Python :: 3.8
Classifier: Programming Language :: Python :: 3.9
Classifier: Programming Language :: Python :: Implementation :: CPython
Requires-Python: >=3.6
Requires-Dist: sphinx (<4,>=3)
Requires-Dist: importlib-resources ; python_version < "3.9"
Provides-Extra: code_style
Requires-Dist: pre-commit (~=2.12) ; extra == 'code_style'
Provides-Extra: myst
Requires-Dist: myst-nb (<0.13,>=0.11) ; extra == 'myst'
Provides-Extra: rtd
Requires-Dist: myst-parser ; extra == 'rtd'
Requires-Dist: sphinx-book-theme ; extra == 'rtd'
Provides-Extra: testing
Requires-Dist: coverage (<5.0) ; extra == 'testing'
Requires-Dist: jupyter-book (<0.12,>=0.11.0a1) ; extra == 'testing'
Requires-Dist: pytest (<4,>=3.6) ; extra == 'testing'
Requires-Dist: pytest-cov (~=2.8) ; extra == 'testing'
Requires-Dist: pytest-regressions ; extra == 'testing'
Requires-Dist: sphinx-external-toc (<0.3.0,>=0.1.0) ; extra == 'testing'
Requires-Dist: sphinxcontrib-bibtex (<2.3.0,>=2.2.1) ; extra == 'testing'
Requires-Dist: texsoup ; extra == 'testing'
